design/design.sv
module bcd_to_excess3(a,b,c,d,w,x,y,z);
  input a,b,c,d;
  output w,x,y,z;
  assign z=~d;
  assign y=(c&d)|(~(c+d));
  assign x=(~b&c)|(~b&d)|(b&~c&~d);
  assign w=a|(b&c)|(b&d);
endmodule

testbench/testbench.sv
module testbench();
  
  //inputs and outputs
  reg[3:0] bcd;
  wire[3:0] excess3;
  
  //dut
  
  bcd_to_excess3 dut(
    .a(bcd[3]),
    .b(bcd[2]),
    .c(bcd[1]),
    .d(bcd[0]),
    .w(excess3[3]),
    .x(excess3[2]),
    .y(excess3[1]),
    .z(excess3[0])
  );
  
  
  //clock and reset values
  reg clk;
  reg rst;
  
  //initial values
  initial begin
    clk=0;
    rst=1;
    #20
    rst=0;
  end
  
  //clock gen
  always begin
    #10 clk=~clk;
  end
  
  
  
  //test seq
  
  reg[3:0] i;
  
  always@(posedge clk, posedge rst) begin
    if(rst) begin
      bcd=0;
      i=0;
    end else begin
      //apply all bcd values
      bcd=i;

      
      if(i==9) begin
        #10
        $finish;
      end
      else begin
        i=i+1;
      end
      
    end
  end
  initial begin
    $monitor("%d: BCD =%b, Excess-3 =%b", $time, bcd, excess3);
  end
  initial begin
    $dumpfile("dump.vcd");
    $dumpvars(0, testbench);
  end
endmodule

simulation/dump.vcd
$date
	Wed Jul  8 14:18:10 2026
$end
$version
	Icarus Verilog
$end
$timescale
	1s
$end
$scope module testbench $end
$var wire 4 ! excess3 [3:0] $end
$var reg 4 " bcd [3:0] $end
$var reg 1 # clk $end
$var reg 4 $ i [3:0] $end
$var reg 1 % rst $end
$scope module dut $end
$var wire 1 & a $end
$var wire 1 ' b $end
$var wire 1 ( c $end
$var wire 1 ) d $end
$var wire 1 * w $end
$var wire 1 + x $end
$var wire 1 , y $end
$var wire 1 - z $end
$upscope $end
$upscope $end
$enddefinitions $end
$comment Show the parameter values. $end
$dumpall
$end
#0
$dumpvars
x-
x,
x+
x*
x)
x(
x'
x&
1%
bx $
0#
bx "
bx !
$end
#10
0+
1,
0*
b11 !
1-
0&
0'
0(
0)
b0 $
b0 "
1#
#20
0#
0%
#30
b1 $
1#
#40
0#
#50
1+
0,
b100 !
0-
1)
b10 $
b1 "
1#
#60
0#
#70
b101 !
1-
1(
0)
b11 $
b10 "
1#
#80
0#
#90
1,
b110 !
0-
1)
b100 $
b11 "
1#
#100
0#
#110
b111 !
1-
1'
0(
0)
b101 $
b100 "
1#
#120
0#
#130
0+
1*
0,
b1000 !
0-
1)
b110 $
b101 "
1#
#140
0#
#150
0+
1*
b1001 !
1-
1(
0)
b111 $
b110 "
1#
#160
0#
#170
1,
b1010 !
0-
1)
b1000 $
b111 "
1#
#180
0#
#190
b1011 !
1-
1&
0'
0(
0)
b1001 $
b1000 "
1#
#200
0#
#210
1+
0,
b1100 !
0-
1)
b1001 "
1#
